cohesion/__init__.py
cohesion/calculations.py
cohesion/formula.py
cohesion/topic_cohesion.py
cohesion/utils.py
cohesion/zero_shot_classifier.py
topic_cohesion-0.1.1.dist-info/LICENSE.txt
topic_cohesion-0.1.1.dist-info/METADATA
topic_cohesion-0.1.1.dist-info/WHEEL
topic_cohesion-0.1.1.dist-info/top_level.txt
topic_cohesion-0.1.1.dist-info/RECORD
