Metadata-Version: 2.1
Name: topic-cohesion
Version: 0.1.1
Summary: Cohesion measurement to evaluate partition
Home-page: https://github.com/TopicCohesion/topic-cohesion
Author: Topic Cohesion
Author-email: topic.cohesion@gmail.com
Classifier: Programming Language :: Python :: 3
Classifier: License :: OSI Approved :: MIT License
Classifier: Operating System :: OS Independent
Requires-Python: ~=3.7
License-File: LICENSE.txt
Requires-Dist: nltk (==3.7)
Requires-Dist: scikit-learn (==1.0.1)
Requires-Dist: pandas (==1.1.5)
Requires-Dist: transformers (==4.20.1)
Requires-Dist: tensorflow (==2.9.1)
Requires-Dist: torch
